distances/__init__.py
distances/_bag.py
distances/_baulieu_xiii.py
distances/_character.py
distances/_clement.py
distances/_cormode_lz.py
distances/_damerau_levenshtein.py
distances/_dice_asymmetric_i.py
distances/_discounted_levenshtein.py
distances/_distance.py
distances/_double_metaphone.py
distances/_editex.py
distances/_fuzzywuzzy_partial_string.py
distances/_fuzzywuzzy_token_set.py
distances/_fuzzywuzzy_token_sort.py
distances/_hamming.py
distances/_indel.py
distances/_iterative_substring.py
distances/_kuhns_iii.py
distances/_lcprefix.py
distances/_lcsseq.py
distances/_levenshtein.py
distances/_lig3.py
distances/_ncd_bz2.py
distances/_overlap.py
distances/_pearson_chi_squared.py
distances/_pearson_ii.py
distances/_phonetic.py
distances/_phonetic_distance.py
distances/_q_grams.py
distances/_q_skipgrams.py
distances/_ratcliff_obershelp.py
distances/_refined_soundex.py
distances/_regexp.py
distances/_rouge_l.py
distances/_ssk.py
distances/_tichy.py
distances/_token_distance.py
distances/_tokenizer.py
distances/_typo.py
distances/_warrens_iv.py
distances/_weighted_jaccard.py
distances/_whitespace.py
name_matching/__init__.py
name_matching/distance_metrics.py
name_matching/name_matcher.py
name_matching/run_nm.py
name_matching/sparse_cosine.py
name_matching-0.8.12.dist-info/METADATA
name_matching-0.8.12.dist-info/WHEEL
name_matching-0.8.12.dist-info/top_level.txt
name_matching-0.8.12.dist-info/RECORD
