Metadata-Version: 2.1
Name: name_matching
Version: 0.8.12
Summary: A package for the matching of company names
Author: Michiel Nijhuis
Author-email: m.nijhuis@dnb.nl
Project-URL: Documentation, https://name-matching.readthedocs.io/en/latest/index.html
Project-URL: Source Code, https://github.com/DeNederlandscheBank/name_matching
Requires-Dist: cleanco
Requires-Dist: scikit-learn
Requires-Dist: pandas
Requires-Dist: numpy
Requires-Dist: tqdm
